{
  "type": "mna:manaweaving-recipe",
  "tier": 3,
  "output": "dmnr:purified_mutandis",
  "quantity": 16,
  "requiredFaction": "mna:fey",
  "items": [
    "dmnr:mutandis",
    "minecraft:egg",
    "minecraft:nether_wart",
    "minecraft:bone_meal",
    "mna:ma_flowers",
    "mna:purified_vinteum_dust",
    "mna:purified_vinteum_dust",
    "mna:purified_vinteum_dust",
    "mna:purified_vinteum_dust"
  ],
  "patterns": [
    "mna:manaweave_patterns/diamond",
    "mna:manaweave_patterns/slash",
    "mna:manaweave_patterns/backslash"
  ]
}