{
  "type": "mna:eldrin-altar",
  "output": "dragonmagicandrelics:upgrade_seal_health_boost_ii",
  "tier": 5,
  "items": [
    "mna:stone_rune_red",
    "minecraft:ghast_tear",
    "minecraft:ghast_tear",
    "minecraft:golden_apple",
    "minecraft:netherite_ingot",
    "mna:rune_defense",
    "mna:rune_defense",
    "minecraft:nether_star",
    "minecraft:nether_star"
  ],
  "power_requirements": [
    {
      "affinity": "EARTH",
      "amount": 1000
    },
    {
      "affinity": "ARCANE",
      "amount": 1000
    }
  ]
}