{
  "type": "mna:eldrin-altar",
  "output": "dragonmagicandrelics:upgrade_seal_health_boost",
  "tier": 5,
  "items": [
    "mna:stone_rune_red",
    "minecraft:ghast_tear",
    "minecraft:iron_chestplate",
    "minecraft:golden_chestplate",
    "minecraft:diamond_chestplate",
    "minecraft:netherite_chestplate",
    "mna:rune_defense",
    "minecraft:nether_star",
    "dragonmagicandrelics:dragon_core"
  ],
  "power_requirements": [
    {
      "affinity": "EARTH",
      "amount": 400
    },
    {
      "affinity": "ARCANE",
      "amount": 200
    }
  ]
}